{
  "tags": [{
    "name": "addressBelongsTocity",
    "description": "Everything about belongs to relation"
  }],
  "paths": {
    "/api/v1/address/belongs/city": {
      "get": {
        "tags": [
          "addressBelongsTocity"
        ],
        "summary": "Get address list with city parent",
        "description": "",
        "operationId": "addressWithParent",
        "produces": [
          "application/json"
        ],
        "parameters": [{
            "in": "query",
            "name": "where",
            "type": "String",
            "description": "Where expression"
          },
          {
            "in": "query",
            "name": "limit",
            "description": "Page size limit",
            "type": "integer",
            "format": "int64"
          },
          {
            "in": "query",
            "name": "offset",
            "description": "Pagination offset",
            "type": "integer",
            "format": "int64"
          },
          {
            "in": "query",
            "name": "sort",
            "description": "Sort parameter",
            "type": "string"
          }
        ],
        "responses": {
          "200": {
            "description": "successful operation",
            "schema": {
              "type": "array",
              "items": {
                "type": "object"
              }
            }
          }
        }
      }
    }
  },
  "definitions": {}
}